opennote/__init__.py
opennote/async_sdk.py
opennote/base_client.py
opennote/sync_sdk.py
opennote/types/__init__.py
opennote/types/api_types.py
opennote/types/block_types.py
opennote/util/__init__.py
opennote/util/edit_operations.py
opennote-2.3.3.dist-info/licenses/LICENSE
opennote-2.3.3.dist-info/METADATA
opennote-2.3.3.dist-info/WHEEL
opennote-2.3.3.dist-info/top_level.txt
opennote-2.3.3.dist-info/RECORD
