Metadata-Version: 2.4
Name: opennote
Version: 2.3.3
Summary: Opennote Python SDK
Home-page: https://github.com/opennote-dev/api-sdk-python
Author: Opennote, Inc.
Author-email: devtools@opennote.me
License: MIT
Classifier: Programming Language :: Python :: 3
Classifier: License :: OSI Approved :: MIT License
Classifier: Operating System :: OS Independent
License-File: LICENSE
Requires-Dist: requests
Requires-Dist: pydantic
Requires-Dist: httpx
Dynamic: author
Dynamic: author-email
Dynamic: classifier
Dynamic: description
Dynamic: description-content-type
Dynamic: home-page
Dynamic: license
Dynamic: license-file
Dynamic: requires-dist
Dynamic: summary
